statiq/__init__.py
statiq/_version.py
statiq/abstract.py
statiq/builder.py
statiq/filters.py
statiq/page.py
statiq/plugin.py
statiq/static.py
statiq/cli/__init__.py
statiq/cli/commands.py
statiq/examples/demo/config.py
statiq/examples/demo/pages/[slug].py
statiq/examples/demo/pages/index.py
statiq/examples/demo/pages/[category]/[page].py
statiq/examples/demo/pages/[category]/index.py
statiq/examples/demo/static/main.css
statiq/examples/demo/templates/[slug].html
statiq/examples/demo/templates/index.html
statiq/examples/demo/templates/[category]/[page].html
statiq/examples/demo/templates/[category]/index.html
statiq/templates/base.html
statiq-0.1.1.dist-info/LICENSE
statiq-0.1.1.dist-info/METADATA
statiq-0.1.1.dist-info/WHEEL
statiq-0.1.1.dist-info/entry_points.txt
statiq-0.1.1.dist-info/top_level.txt
statiq-0.1.1.dist-info/RECORD
