Metadata-Version: 2.1
Name: statiq
Version: 0.1.1
Summary: Statiq is a static site generator
Author-email: Marcin Giziński <ooizig@gmail.com>, Krzysztof Koziarek <krzynio@gmail.com>
License: MIT License
Project-URL: repository, http://github.com/pystatiq/statiq
Project-URL: homepage, http://github.com/pystatiq/statiq
Classifier: License :: OSI Approved :: MIT License
Classifier: Programming Language :: Python :: 3.11
License-File: LICENSE
Requires-Dist: Jinja2 >=3.1.2
Requires-Dist: importlib-metadata ; python_version < "3.8"
